sage/cli/__init__.py
sage/cli/_version.py
sage/cli/main.py
sage/cli/commands/__init__.py
sage/cli/commands/apps/__init__.py
sage/cli/commands/apps/chat.py
sage/cli/commands/apps/edge.py
sage/cli/commands/apps/embedding.py
sage/cli/commands/apps/gateway.py
sage/cli/commands/apps/inference.py
sage/cli/commands/apps/llm.py
sage/cli/commands/apps/pipeline.py
sage/cli/commands/apps/pipeline_domain.py
sage/cli/commands/apps/pipeline_embedding.py
sage/cli/commands/apps/pipeline_knowledge.py
sage/cli/commands/apps/studio.py
sage/cli/commands/platform/__init__.py
sage/cli/commands/platform/cluster.py
sage/cli/commands/platform/config.py
sage/cli/commands/platform/docs.py
sage/cli/commands/platform/doctor.py
sage/cli/commands/platform/env.py
sage/cli/commands/platform/extensions.py
sage/cli/commands/platform/head.py
sage/cli/commands/platform/job.py
sage/cli/commands/platform/jobmanager.py
sage/cli/commands/platform/llm_config.py
sage/cli/commands/platform/ray_version_checker.py
sage/cli/commands/platform/ssh_setup.py
sage/cli/commands/platform/version.py
sage/cli/commands/platform/worker.py
sage/cli/core/__init__.py
sage/cli/core/base.py
sage/cli/core/config.py
sage/cli/core/config_refactored.py
sage/cli/core/exceptions.py
sage/cli/core/output.py
sage/cli/core/refactor_example.py
sage/cli/core/ssh.py
sage/cli/core/utils.py
sage/cli/core/validation.py
sage/cli/management/__init__.py
sage/cli/management/config_manager.py
sage/cli/management/deployment_manager.py
sage/cli/templates/__init__.py
sage/cli/templates/catalog.py
sage/cli/templates/pipeline_blueprints.py
sage/cli/utils/__init__.py
sage/cli/utils/dev_check.py
sage/cli/utils/diagnostics.py
sage/cli/utils/env.py
sage/cli/utils/llm_detection.py
isage_cli-0.2.3.2.dist-info/METADATA
isage_cli-0.2.3.2.dist-info/WHEEL
isage_cli-0.2.3.2.dist-info/entry_points.txt
isage_cli-0.2.3.2.dist-info/top_level.txt
isage_cli-0.2.3.2.dist-info/RECORD
