Metadata-Version: 2.4
Name: isage-cli
Version: 0.2.3.2
Summary: SAGE Command Line Interface - Unified CLI for SAGE platform
Author-email: IntelliStream Team <shuhao_zhang@hust.edu.cn>
License: MIT
Project-URL: Homepage, https://github.com/intellistream/SAGE
Project-URL: Documentation, https://intellistream.github.io/SAGE
Project-URL: Repository, https://github.com/intellistream/SAGE
Project-URL: Issues, https://github.com/intellistream/SAGE/issues
Keywords: sage,cli,command-line,streaming,ai
Classifier: Development Status :: 4 - Beta
Classifier: Intended Audience :: Developers
Classifier: Programming Language :: Python :: 3
Classifier: Programming Language :: Python :: 3.11
Classifier: Programming Language :: Python :: 3.12
Requires-Python: >=3.11
Requires-Dist: typer<1.0.0,>=0.15.0
Requires-Dist: rich<14.0.0,>=13.0.0
Requires-Dist: pyyaml>=6.0
Requires-Dist: python-dotenv<2.0.0,>=1.1.0
Requires-Dist: httpx<1.0.0,>=0.28.0
Requires-Dist: colorama>=0.4.6
Requires-Dist: tabulate<1.0.0,>=0.9.0
Provides-Extra: dev
Requires-Dist: pytest>=7.4.0; extra == "dev"
Requires-Dist: pytest-cov>=4.0.0; extra == "dev"
Requires-Dist: ruff==0.14.6; extra == "dev"
Requires-Dist: mypy>=1.7.0; extra == "dev"
Provides-Extra: all
